locatecolorcluster/README.MD
locatecolorcluster/__init__.py
locatecolorcluster/requirements.txt
locatecolorcluster/thirdparty.json
locatecolorcluster-0.10.dist-info/LICENSE.rst
locatecolorcluster-0.10.dist-info/METADATA
locatecolorcluster-0.10.dist-info/WHEEL
locatecolorcluster-0.10.dist-info/top_level.txt
locatecolorcluster-0.10.dist-info/RECORD
