Metadata-Version: 2.1
Name: locatecolorcluster
Version: 0.10
Summary: Lightning-fast image color clustering with C-based RGB localization/euclidean distance calculation. Supports DBSCAN/HDBSCAN, Shapely geometry.
Home-page: https://github.com/hansalemaos/locatecolorcluster
Author: Johannes Fischer
Author-email: aulasparticularesdealemaosp@gmail.com
License: MIT
Keywords: DBSCAN,HDBSCAN,euclidean
Classifier: Development Status :: 4 - Beta
Classifier: Programming Language :: Python :: 3 :: Only
Classifier: Programming Language :: Python :: 3.10
Classifier: Topic :: Software Development :: Libraries :: Python Modules
Classifier: Topic :: Utilities
License-File: LICENSE.rst
Requires-Dist: Shapely
Requires-Dist: a-cv2-easy-resize
Requires-Dist: a-cv-imwrite-imread-plus
Requires-Dist: cythoneuclideandistance
Requires-Dist: locate-pixelcolor-c
Requires-Dist: numexpr
Requires-Dist: numpy
Requires-Dist: opencv-python
Requires-Dist: scikit-learn
Requires-Dist: scipy
